<annotation>
	<folder>dataset</folder>
	<filename>armas (24).jpg</filename>
	<path>C:\Users\islyambek.kairov\Documents\www\gun\dataset\armas (24).jpg</path>
	<source>
		<database>Unknown</database>
	</source>
	<size>
		<width>662</width>
		<height>440</height>
		<depth>3</depth>
	</size>
	<segmented>0</segmented>
	<object>
		<name>gun</name>
		<pose>Unspecified</pose>
		<truncated>0</truncated>
		<difficult>0</difficult>
		<bndbox>
			<xmin>314</xmin>
			<ymin>71</ymin>
			<xmax>647</xmax>
			<ymax>299</ymax>
		</bndbox>
	</object>
</annotation>
