<annotation>
	<folder>dataset</folder>
	<filename>armas (226).jpg</filename>
	<path>C:\Users\islyambek.kairov\Documents\www\gun\dataset\armas (226).jpg</path>
	<source>
		<database>Unknown</database>
	</source>
	<size>
		<width>1300</width>
		<height>1065</height>
		<depth>3</depth>
	</size>
	<segmented>0</segmented>
	<object>
		<name>gun</name>
		<pose>Unspecified</pose>
		<truncated>0</truncated>
		<difficult>0</difficult>
		<bndbox>
			<xmin>631</xmin>
			<ymin>541</ymin>
			<xmax>795</xmax>
			<ymax>749</ymax>
		</bndbox>
	</object>
</annotation>
