<annotation>
	<folder>dataset</folder>
	<filename>armas (89).jpg</filename>
	<path>C:\Users\islyambek.kairov\Documents\www\gun\dataset\armas (89).jpg</path>
	<source>
		<database>Unknown</database>
	</source>
	<size>
		<width>168</width>
		<height>113</height>
		<depth>3</depth>
	</size>
	<segmented>0</segmented>
	<object>
		<name>gun</name>
		<pose>Unspecified</pose>
		<truncated>0</truncated>
		<difficult>0</difficult>
		<bndbox>
			<xmin>34</xmin>
			<ymin>27</ymin>
			<xmax>52</xmax>
			<ymax>76</ymax>
		</bndbox>
	</object>
</annotation>
